easy_django_setup/__init__.py
easy_django_setup/cli.py
easy_django_setup-0.1.4.dist-info/METADATA
easy_django_setup-0.1.4.dist-info/WHEEL
easy_django_setup-0.1.4.dist-info/entry_points.txt
easy_django_setup-0.1.4.dist-info/top_level.txt
easy_django_setup-0.1.4.dist-info/RECORD
