Metadata-Version: 2.1
Name: easy-django-setup
Version: 0.1.4
Summary: Easy Django Setup Tool
Home-page: https://github.com/curl-kawsar/easy_django_setup
Author: Kawsar
Author-email: knownaskawsar@example.com
Classifier: Programming Language :: Python :: 3
Classifier: License :: OSI Approved :: MIT License
Classifier: Operating System :: OS Independent
Requires-Python: >=3.6
Requires-Dist: click
Requires-Dist: Django
Requires-Dist: djangorestframework
Requires-Dist: django-allauth
Requires-Dist: django-redis
Requires-Dist: django-storages
Requires-Dist: cloudinary
Requires-Dist: drf-yasg
